excel_template_app/__init__.py
excel_template_app/app.py
excel_template_app-0.1.1.dist-info/LICENSE
excel_template_app-0.1.1.dist-info/METADATA
excel_template_app-0.1.1.dist-info/WHEEL
excel_template_app-0.1.1.dist-info/entry_points.txt
excel_template_app-0.1.1.dist-info/top_level.txt
excel_template_app-0.1.1.dist-info/RECORD
